alwaysontop_tooltip/__init__.py
alwaysontop_tooltip/alwaysontop_tooltip.py
alwaysontop_tooltip-1.3.dist-info/METADATA
alwaysontop_tooltip-1.3.dist-info/WHEEL
alwaysontop_tooltip-1.3.dist-info/top_level.txt
alwaysontop_tooltip-1.3.dist-info/RECORD
